pyhttps/__init__.py
pyhttps/__main__.py
pyhttps/pyhttps.py
py_https-0.0.2.1.dist-info/LICENSE
py_https-0.0.2.1.dist-info/METADATA
py_https-0.0.2.1.dist-info/WHEEL
py_https-0.0.2.1.dist-info/top_level.txt
py_https-0.0.2.1.dist-info/RECORD
