Metadata-Version: 2.1
Name: py-https
Version: 0.0.2.1
Summary: A simple python https server
Home-page: https://github.com/avinashkarhana/py-https
Author: Avinash Karhana
Author-email: avinashkarhana1@gmail.com
License: UNKNOWN
Keywords: https,pyhttps,https.server,pyhttps.server
Platform: UNKNOWN
Classifier: Programming Language :: Python :: 3
Classifier: Programming Language :: Python :: 3.6
Classifier: Programming Language :: Python :: 3.7
Classifier: Programming Language :: Python :: 3.8
Classifier: Programming Language :: Python :: 3.9
Classifier: Programming Language :: Python :: 3.10
Classifier: License :: OSI Approved :: MIT License
Classifier: Operating System :: OS Independent
Requires-Python: >=3.5
